{"4YA9IqKhKEAtgUbqLHTGIQ==":"mbr-3.jpg","GzIQatjyCAfcMmw3qwvmMg==":"mbr-4.jpg","hE5TvlyVY6cX3o0Wxsnp/A==":"mbr-5.jpg","1PZvAdu0mdOW1M6qPo6x3w==":"mbr-6.jpg","EoL+vB482itxMf7fBy1SRw==":"mbr.jpg","sKGpmdsmO83ga+kxZJlU0Q==":"lily-banse--yhswy6uqvk-unsplash-2000x1333.jpg","UCwVrvMhJXceNn3HPJWEGA==":"vitalii-chernopyskyi-oxb84encffu-unsplash-948x632.jpg","DgORnnjc5M+qxuIdJO3NQw==":"screenshot%202022-07-31%20225216-544x529.png","tlJSQUBeaeuj2RUuDBgwKA==":"screenshot%202022-07-31%20225427-390x456.png","NVP5dBNEAdn3vW5xaul7nw==":"screenshot%202022-07-31%20225351-395x288.png"}